<annotation>
	<folder>dataset_genannotations</folder>
	<filename>2019_07_25_01_44_40250.png</filename>
	<source>my_randomgazebomanager_pkg</source>
	<size>
		<depth>3</depth>
	<width>640</width><height>480</height></size>
	<segmented>0</segmented>
	
<object><name>coffee_cup1</name><pose3d><x_com>0.7981198330268156</x_com><y_com>-0.13425697910322323</y_com><z_com>0.7548244215633382</z_com><quat_x>0.018672043189656498</quat_x><quat_y>0.004105977182637642</quat_y><quat_z>0.0005530442880074575</quat_z><quat_w>0.9998170782180682</quat_w></pose3d></object></annotation>