<annotation>
	<folder>dataset_genannotations</folder>
	<filename>2019_07_22_21_36_31236.png</filename>
	<source>my_randomgazebomanager_pkg</source>
	<size>
		<depth>3</depth>
	<width>640</width><height>480</height></size>
	<segmented>0</segmented>
	
<object><name>coffee_cup1</name><pose3d><x_com>0.7599220649446724</x_com><y_com>-0.056513475395724995</y_com><z_com>0.7549927339071228</z_com><quat_x>0.0005700997664134318</quat_x><quat_y>0.00011311874890838959</quat_y><quat_z>-0.02014834273243847</quat_z><quat_w>0.9997968325992743</quat_w></pose3d></object></annotation>