<annotation>
	<folder>dataset_genannotations</folder>
	<filename>2019_07_22_21_36_30032.png</filename>
	<source>my_randomgazebomanager_pkg</source>
	<size>
		<depth>3</depth>
	<width>640</width><height>480</height></size>
	<segmented>0</segmented>
	
<object><name>coffee_cup1</name><pose3d><x_com>0.22873160370708062</x_com><y_com>-0.15963060000251886</y_com><z_com>0.0002176876926453401</z_com><quat_x>-0.0015630600822626101</quat_x><quat_y>-0.0049258740195653235</quat_y><quat_z>0.9906382898188532</quat_z><quat_w>0.13641507010994167</quat_w></pose3d></object></annotation>