<annotation>
	<folder>dataset_genannotations</folder>
	<filename>2019_07_24_16_22_43026.png</filename>
	<source>my_randomgazebomanager_pkg</source>
	<size>
		<depth>3</depth>
	<width>640</width><height>480</height></size>
	<segmented>0</segmented>
	
<object><name>coffee_cup1</name><pose3d><x_com>0.561366733689041</x_com><y_com>0.15511957204193005</y_com><z_com>0.7549880738695897</z_com><quat_x>0.0009007781997863309</quat_x><quat_y>0.0001907614252621391</quat_y><quat_z>-0.001629760707602736</quat_z><quat_w>0.9999982480428401</quat_w></pose3d></object></annotation>