<annotation>
	<folder>dataset_genannotations</folder>
	<filename>2019_07_24_16_22_43013.png</filename>
	<source>my_randomgazebomanager_pkg</source>
	<size>
		<depth>3</depth>
	<width>640</width><height>480</height></size>
	<segmented>0</segmented>
	
<object><name>coffee_cup1</name><pose3d><x_com>0.41635403594024684</x_com><y_com>-0.11731631150405125</y_com><z_com>-1.6888186829520945e-05</z_com><quat_x>0.00039490245375397594</quat_x><quat_y>-0.0010338953361941985</quat_y><quat_z>-0.00403905357492172</quat_z><quat_w>0.9999912305409008</quat_w></pose3d></object></annotation>