<annotation>
	<folder>dataset_genannotations</folder>
	<filename>2019_07_17_20_04_6538.png</filename>
	<source>my_randomgazebomanager_pkg</source>
	<size>
		<depth>3</depth>
	<width>640</width><height>480</height></size>
	<segmented>0</segmented>
	
<object><name>coffee_cup1</name><pose3d><x_com>0.757415238556321</x_com><y_com>0.15065583114646758</y_com><z_com>0.7550010632856705</z_com><quat_x>0.0001183076987053722</quat_x><quat_y>-1.4800166426158483e-05</quat_y><quat_z>-0.004701252291508353</quat_z><quat_w>0.9999889419444272</quat_w></pose3d></object></annotation>