<annotation>
	<folder>dataset_genannotations</folder>
	<filename>2019_07_24_16_22_41473.png</filename>
	<source>my_randomgazebomanager_pkg</source>
	<size>
		<depth>3</depth>
	<width>640</width><height>480</height></size>
	<segmented>0</segmented>
	
<object><name>coffee_cup1</name><pose3d><x_com>0.4680810751246881</x_com><y_com>0.03242765695292959</y_com><z_com>0.759174792489992</z_com><quat_x>0.0964476591295842</quat_x><quat_y>0.014815168358144575</quat_y><quat_z>-0.2810229171702326</quat_z><quat_w>0.9547274374710703</quat_w></pose3d></object></annotation>