<annotation>
	<folder>dataset_genannotations</folder>
	<filename>2019_07_24_16_22_42882.png</filename>
	<source>my_randomgazebomanager_pkg</source>
	<size>
		<depth>3</depth>
	<width>640</width><height>480</height></size>
	<segmented>0</segmented>
	
<object><name>coffee_cup1</name><pose3d><x_com>0.7173723875123028</x_com><y_com>-0.2000982339831492</y_com><z_com>0.7549969801610299</z_com><quat_x>0.00027912722999338474</quat_x><quat_y>1.8346856161312934e-05</quat_y><quat_z>-0.009935331258669671</quat_z><quat_w>0.9999506042521116</quat_w></pose3d></object></annotation>