<annotation>
	<folder>dataset_genannotations</folder>
	<filename>2019_07_17_20_04_3019.png</filename>
	<source>my_randomgazebomanager_pkg</source>
	<size>
		<depth>3</depth>
	<width>640</width><height>480</height></size>
	<segmented>0</segmented>
	
<object><name>coffee_cup1</name><pose3d><x_com>0.6818061711302479</x_com><y_com>0.06857921825755878</y_com><z_com>0.7593883454310804</z_com><quat_x>0.05366945833154386</quat_x><quat_y>0.08798774188785764</quat_y><quat_z>-0.052287697937490066</quat_z><quat_w>0.9932994227141543</quat_w></pose3d></object></annotation>