<annotation>
	<folder>dataset_genannotations</folder>
	<filename>2019_07_24_16_22_41213.png</filename>
	<source>my_randomgazebomanager_pkg</source>
	<size>
		<depth>3</depth>
	<width>640</width><height>480</height></size>
	<segmented>0</segmented>
	
<object><name>coffee_cup1</name><pose3d><x_com>0.43366908107068086</x_com><y_com>0.19455255538778785</y_com><z_com>0.000916509174395503</z_com><quat_x>0.005386865555084042</quat_x><quat_y>-0.03362556382170661</quat_y><quat_z>-0.2711626738410746</quat_z><quat_w>0.9619309265495746</quat_w></pose3d></object></annotation>