<annotation>
	<folder>dataset_genannotations</folder>
	<filename>2019_07_17_20_04_1039.png</filename>
	<source>my_randomgazebomanager_pkg</source>
	<size>
		<depth>3</depth>
	<width>640</width><height>480</height></size>
	<segmented>0</segmented>
	
<object><name>coffee_cup1</name><pose3d><x_com>0.3864975618317992</x_com><y_com>-0.10338422926051062</y_com><z_com>0.02102845690882705</z_com><quat_x>0.312733352429015</quat_x><quat_y>-0.555537043337338</quat_y><quat_z>0.1681360837329558</quat_z><quat_w>0.7518688057802787</quat_w></pose3d></object></annotation>