<annotation>
	<folder>dataset_genannotations</folder>
	<filename>2019_07_28_19_55_49199.png</filename>
	<source>my_randomgazebomanager_pkg</source>
	<size>
		<depth>3</depth>
	<width>640</width><height>480</height></size>
	<segmented>0</segmented>
	
<object><name>coffee_cup1</name><pose3d><x_com>0.7472535394584915</x_com><y_com>0.10680971454959881</y_com><z_com>0.7689230025395195</z_com><quat_x>-0.0607552067398743</quat_x><quat_y>0.3408726518317737</quat_y><quat_z>0.11843173982982623</quat_z><quat_w>-0.9306387930276977</quat_w></pose3d></object></annotation>