<annotation>
	<folder>dataset_genannotations</folder>
	<filename>2019_07_18_22_08_18671.png</filename>
	<source>my_randomgazebomanager_pkg</source>
	<size>
		<depth>3</depth>
	<width>640</width><height>480</height></size>
	<segmented>0</segmented>
	
<object><name>coffee_cup1</name><pose3d><x_com>0.628533292446918</x_com><y_com>0.11669048443202089</y_com><z_com>0.7549923903414678</z_com><quat_x>3.502151415599151e-05</quat_x><quat_y>-0.00022996865249903467</quat_y><quat_z>-0.4355319897118864</quat_z><quat_w>0.9001732232329053</quat_w></pose3d></object></annotation>