<annotation>
	<folder>dataset_genannotations</folder>
	<filename>2019_07_23_16_42_39414.png</filename>
	<source>my_randomgazebomanager_pkg</source>
	<size>
		<depth>3</depth>
	<width>640</width><height>480</height></size>
	<segmented>0</segmented>
	
<object><name>coffee_cup1</name><pose3d><x_com>0.5458309310957277</x_com><y_com>-0.12553455782237063</y_com><z_com>0.7549897714014788</z_com><quat_x>0.0013182290355076484</quat_x><quat_y>0.0001932201280960677</quat_y><quat_z>0.11227381433422233</quat_z><quat_w>0.9936764139059739</quat_w></pose3d></object></annotation>