<annotation>
	<folder>dataset_genannotations</folder>
	<filename>2019_07_23_08_15_33512.png</filename>
	<source>my_randomgazebomanager_pkg</source>
	<size>
		<depth>3</depth>
	<width>640</width><height>480</height></size>
	<segmented>0</segmented>
	
<object><name>coffee_cup1</name><pose3d><x_com>0.6672803508154495</x_com><y_com>0.14669067353131762</y_com><z_com>0.7754733707561005</z_com><quat_x>-0.13390121116443665</quat_x><quat_y>-0.6425635643929749</quat_y><quat_z>-0.14206559904122906</quat_z><quat_w>0.7409452725622512</quat_w></pose3d></object></annotation>