<annotation>
	<folder>dataset_genannotations</folder>
	<filename>2019_07_23_08_15_34146.png</filename>
	<source>my_randomgazebomanager_pkg</source>
	<size>
		<depth>3</depth>
	<width>640</width><height>480</height></size>
	<segmented>0</segmented>
	
<object><name>coffee_cup1</name><pose3d><x_com>0.7789326946061956</x_com><y_com>-0.0810103554214652</y_com><z_com>0.76824849094581</z_com><quat_x>-0.1039806524785874</quat_x><quat_y>-0.30639897713333053</quat_y><quat_z>0.1957640215207851</quat_z><quat_w>0.9257343779939177</quat_w></pose3d></object></annotation>