<annotation>
	<folder>dataset_genannotations</folder>
	<filename>2019_07_17_20_04_3113.png</filename>
	<source>my_randomgazebomanager_pkg</source>
	<size>
		<depth>3</depth>
	<width>640</width><height>480</height></size>
	<segmented>0</segmented>
	
<object><name>coffee_cup1</name><pose3d><x_com>0.6213808468513401</x_com><y_com>0.12477463905969437</y_com><z_com>0.7549889285034123</z_com><quat_x>0.0002609902494100275</quat_x><quat_y>-0.0002475605498521083</quat_y><quat_z>7.800841337653483e-05</quat_z><quat_w>0.9999999322562735</quat_w></pose3d></object></annotation>