<annotation>
	<folder>dataset_genannotations</folder>
	<filename>2019_07_19_15_12_26495.png</filename>
	<source>my_randomgazebomanager_pkg</source>
	<size>
		<depth>3</depth>
	<width>640</width><height>480</height></size>
	<segmented>0</segmented>
	
<object><name>coffee_cup1</name><pose3d><x_com>0.7565929628214814</x_com><y_com>-0.11570118335538244</y_com><z_com>0.7553692797865869</z_com><quat_x>0.012751058351749143</quat_x><quat_y>0.0062079807364666725</quat_y><quat_z>0.07449897947759158</quat_z><quat_w>0.9971202402633714</quat_w></pose3d></object></annotation>