<annotation>
	<folder>dataset_genannotations</folder>
	<filename>2019_07_18_22_08_19866.png</filename>
	<source>my_randomgazebomanager_pkg</source>
	<size>
		<depth>3</depth>
	<width>640</width><height>480</height></size>
	<segmented>0</segmented>
	
<object><name>coffee_cup1</name><pose3d><x_com>0.6214552836127948</x_com><y_com>-0.15696127864710369</y_com><z_com>0.7550664346086116</z_com><quat_x>0.0017844630663587638</quat_x><quat_y>-0.0007167199439124419</quat_y><quat_z>0.1913263979370877</quat_z><quat_w>0.9815245852532201</quat_w></pose3d></object></annotation>