<annotation>
	<folder>dataset_genannotations</folder>
	<filename>2019_07_18_22_08_12889.png</filename>
	<source>my_randomgazebomanager_pkg</source>
	<size>
		<depth>3</depth>
	<width>640</width><height>480</height></size>
	<segmented>0</segmented>
	
<object><name>coffee_cup1</name><pose3d><x_com>0.5747102082816256</x_com><y_com>-0.10914868058136522</y_com><z_com>0.7541303809655375</z_com><quat_x>6.723559454721433e-05</quat_x><quat_y>-7.306665424179055e-05</quat_y><quat_z>2.2690540226755967e-06</quat_z><quat_w>0.9999999950677451</quat_w></pose3d></object></annotation>