<annotation>
	<folder>dataset_genannotations</folder>
	<filename>2019_07_19_15_12_29672.png</filename>
	<source>my_randomgazebomanager_pkg</source>
	<size>
		<depth>3</depth>
	<width>640</width><height>480</height></size>
	<segmented>0</segmented>
	
<object><name>coffee_cup1</name><pose3d><x_com>0.7172516955269869</x_com><y_com>0.18938639311351693</y_com><z_com>0.754993032966921</z_com><quat_x>0.00045390736605397487</quat_x><quat_y>7.484769915688476e-06</quat_y><quat_z>0.0308825427525917</quat_z><quat_w>0.999522917428718</quat_w></pose3d></object></annotation>