<annotation>
	<folder>dataset_genannotations</folder>
	<filename>2019_07_19_15_12_29344.png</filename>
	<source>my_randomgazebomanager_pkg</source>
	<size>
		<depth>3</depth>
	<width>640</width><height>480</height></size>
	<segmented>0</segmented>
	
<object><name>coffee_cup1</name><pose3d><x_com>0.7039451303310384</x_com><y_com>-0.16506877515296892</y_com><z_com>0.753265824031284</z_com><quat_x>7.596098563937492e-05</quat_x><quat_y>-8.750932759473823e-05</quat_y><quat_z>5.168988003844514e-06</quat_z><quat_w>0.9999999932726639</quat_w></pose3d></object></annotation>