<annotation>
	<folder>dataset_genannotations</folder>
	<filename>2019_07_17_20_04_9429.png</filename>
	<source>my_randomgazebomanager_pkg</source>
	<size>
		<depth>3</depth>
	<width>640</width><height>480</height></size>
	<segmented>0</segmented>
	
<object><name>coffee_cup1</name><pose3d><x_com>0.34092208119049544</x_com><y_com>-0.04665743925132121</y_com><z_com>0.022096160866750272</z_com><quat_x>0.660661821416852</quat_x><quat_y>-0.053880455933271725</quat_y><quat_z>-0.10576841574413354</quat_z><quat_w>-0.7412394325867767</quat_w></pose3d></object></annotation>