<annotation>
	<folder>dataset_genannotations</folder>
	<filename>2019_07_17_20_04_8219.png</filename>
	<source>my_randomgazebomanager_pkg</source>
	<size>
		<depth>3</depth>
	<width>640</width><height>480</height></size>
	<segmented>0</segmented>
	
<object><name>coffee_cup1</name><pose3d><x_com>0.23881423556654122</x_com><y_com>0.12300042605713613</y_com><z_com>0.009745807166291696</z_com><quat_x>0.011606626302454839</quat_x><quat_y>-0.07687046192049439</quat_y><quat_z>0.05004011117516701</quat_z><quat_w>-0.9957169304494033</quat_w></pose3d></object></annotation>