<annotation>
	<folder>dataset_genannotations</folder>
	<filename>2019_07_17_17_45_1005.png</filename>
	<source>my_randomgazebomanager_pkg</source>
	<size>
		<depth>3</depth>
	<width>640</width><height>480</height></size>
	<segmented>0</segmented>
	
<object><name>coffee_cup1</name><pose3d><x_com>0.7998297760363613</x_com><y_com>-0.09395658217453502</y_com><z_com>0.7549880417216565</z_com><quat_x>0.00015350266718364532</quat_x><quat_y>-0.00018760462165307953</quat_y><quat_z>-0.0007091375517141903</quat_z><quat_w>0.9999997191826456</quat_w></pose3d></object></annotation>