<annotation>
	<folder>dataset_genannotations</folder>
	<filename>2019_07_25_03_28_45750.png</filename>
	<source>my_randomgazebomanager_pkg</source>
	<size>
		<depth>3</depth>
	<width>640</width><height>480</height></size>
	<segmented>0</segmented>
	
<object><name>coffee_cup1</name><pose3d><x_com>0.6337846943604372</x_com><y_com>-0.11177251083335317</y_com><z_com>0.7549923560397921</z_com><quat_x>0.00013692280631336627</quat_x><quat_y>-0.0001615474565471745</quat_y><quat_z>-0.007730931175927604</quat_z><quat_w>0.9999700934816589</quat_w></pose3d></object></annotation>