<annotation>
	<folder>dataset_genannotations</folder>
	<filename>2019_07_25_03_28_45076.png</filename>
	<source>my_randomgazebomanager_pkg</source>
	<size>
		<depth>3</depth>
	<width>640</width><height>480</height></size>
	<segmented>0</segmented>
	
<object><name>coffee_cup1</name><pose3d><x_com>0.59191408187791</x_com><y_com>0.16965487499740287</y_com><z_com>0.7762604141545869</z_com><quat_x>-0.07928508741125645</quat_x><quat_y>-0.6535998141184586</quat_y><quat_z>-0.0957659079059765</quat_z><quat_w>0.7465588046372836</quat_w></pose3d></object></annotation>