<annotation>
	<folder>dataset_genannotations</folder>
	<filename>2019_07_25_03_28_42545.png</filename>
	<source>my_randomgazebomanager_pkg</source>
	<size>
		<depth>3</depth>
	<width>640</width><height>480</height></size>
	<segmented>0</segmented>
	
<object><name>coffee_cup1</name><pose3d><x_com>0.6356503892255269</x_com><y_com>0.1480585843138537</y_com><z_com>0.756299651307051</z_com><quat_x>-0.014885117403722878</quat_x><quat_y>0.02796243334969296</quat_y><quat_z>0.007220138420844728</quat_z><quat_w>0.9994720632425026</quat_w></pose3d></object></annotation>