<annotation>
	<folder>dataset_genannotations</folder>
	<filename>2019_07_24_16_22_44608.png</filename>
	<source>my_randomgazebomanager_pkg</source>
	<size>
		<depth>3</depth>
	<width>640</width><height>480</height></size>
	<segmented>0</segmented>
	
<object><name>coffee_cup1</name><pose3d><x_com>0.7962917712801225</x_com><y_com>0.1630404885223704</y_com><z_com>0.7549997618623085</z_com><quat_x>4.515492135837404e-05</quat_x><quat_y>-2.8404920102584277e-05</quat_y><quat_z>-0.0008718122887831955</quat_z><quat_w>0.9999996185486907</quat_w></pose3d></object></annotation>