<annotation>
	<folder>dataset_genannotations</folder>
	<filename>2019_07_23_08_15_32497.png</filename>
	<source>my_randomgazebomanager_pkg</source>
	<size>
		<depth>3</depth>
	<width>640</width><height>480</height></size>
	<segmented>0</segmented>
	
<object><name>coffee_cup1</name><pose3d><x_com>0.5164307932120723</x_com><y_com>0.19152472266896012</y_com><z_com>0.7541548292116895</z_com><quat_x>0.005162100971298168</quat_x><quat_y>-0.006286097663977204</quat_y><quat_z>2.169190197593579e-05</quat_z><quat_w>0.9999669180623839</quat_w></pose3d></object></annotation>