<annotation>
	<folder>dataset_genannotations</folder>
	<filename>2019_07_17_20_04_2148.png</filename>
	<source>my_randomgazebomanager_pkg</source>
	<size>
		<depth>3</depth>
	<width>640</width><height>480</height></size>
	<segmented>0</segmented>
	
<object><name>coffee_cup1</name><pose3d><x_com>0.5866111405740834</x_com><y_com>-0.1802404894004922</y_com><z_com>0.754967129535442</z_com><quat_x>0.0037905813052082436</quat_x><quat_y>0.0007159945333286152</quat_y><quat_z>6.750024396143741e-05</quat_z><quat_w>0.9999925571167587</quat_w></pose3d></object></annotation>