<annotation>
	<folder>dataset_genannotations</folder>
	<filename>2019_07_19_15_12_26668.png</filename>
	<source>my_randomgazebomanager_pkg</source>
	<size>
		<depth>3</depth>
	<width>640</width><height>480</height></size>
	<segmented>0</segmented>
	
<object><name>coffee_cup1</name><pose3d><x_com>0.40160484356587317</x_com><y_com>-0.157765003712732</y_com><z_com>-0.002080231452014645</z_com><quat_x>0.029136923792771004</quat_x><quat_y>0.000977457546587387</quat_y><quat_z>-0.029574017724881455</quat_z><quat_w>0.9991373587871928</quat_w></pose3d></object></annotation>