<annotation>
	<folder>dataset_genannotations</folder>
	<filename>2019_07_18_22_08_19177.png</filename>
	<source>my_randomgazebomanager_pkg</source>
	<size>
		<depth>3</depth>
	<width>640</width><height>480</height></size>
	<segmented>0</segmented>
	
<object><name>coffee_cup1</name><pose3d><x_com>0.2087591775074798</x_com><y_com>0.22740588671575532</y_com><z_com>0.0033321616589525728</z_com><quat_x>0.07413062579196658</quat_x><quat_y>-0.02384772323150685</quat_y><quat_z>-0.9682691280442636</quat_z><quat_w>0.23746753902958317</quat_w></pose3d></object></annotation>