<annotation>
	<folder>dataset_genannotations</folder>
	<filename>2019_07_17_20_04_3277.png</filename>
	<source>my_randomgazebomanager_pkg</source>
	<size>
		<depth>3</depth>
	<width>640</width><height>480</height></size>
	<segmented>0</segmented>
	
<object><name>coffee_cup1</name><pose3d><x_com>0.34064148567774233</x_com><y_com>0.14064408396922906</y_com><z_com>0.01639696912486493</z_com><quat_x>0.3255851846470332</quat_x><quat_y>0.2666740085562341</quat_y><quat_z>0.5321777360351336</quat_z><quat_w>-0.7346197097597003</quat_w></pose3d></object></annotation>