<annotation>
	<folder>dataset_genannotations</folder>
	<filename>2019_07_17_20_04_4010.png</filename>
	<source>my_randomgazebomanager_pkg</source>
	<size>
		<depth>3</depth>
	<width>640</width><height>480</height></size>
	<segmented>0</segmented>
	
<object><name>coffee_cup1</name><pose3d><x_com>0.6679371523747603</x_com><y_com>0.18801564012683522</y_com><z_com>0.7549626481465128</z_com><quat_x>0.006344202887446108</quat_x><quat_y>0.000345350703427994</quat_y><quat_z>-0.00036258275653436333</quat_z><quat_w>0.9999797499731479</quat_w></pose3d></object></annotation>