<annotation>
	<folder>dataset_genannotations</folder>
	<filename>2019_07_24_16_22_44680.png</filename>
	<source>my_randomgazebomanager_pkg</source>
	<size>
		<depth>3</depth>
	<width>640</width><height>480</height></size>
	<segmented>0</segmented>
	
<object><name>coffee_cup1</name><pose3d><x_com>0.5068031789977854</x_com><y_com>0.07564951399072027</y_com><z_com>0.7552318109245542</z_com><quat_x>-0.0025374609826251896</quat_x><quat_y>-0.004738858807721063</quat_y><quat_z>-0.00985791267103979</quat_z><quat_w>0.9999369610464114</quat_w></pose3d></object></annotation>