<annotation>
	<folder>dataset_genannotations</folder>
	<filename>2019_07_22_21_36_31112.png</filename>
	<source>my_randomgazebomanager_pkg</source>
	<size>
		<depth>3</depth>
	<width>640</width><height>480</height></size>
	<segmented>0</segmented>
	
<object><name>coffee_cup1</name><pose3d><x_com>0.7190356624499389</x_com><y_com>-0.02086794485694208</y_com><z_com>0.7549948216181889</z_com><quat_x>0.0004754259460920895</quat_x><quat_y>-5.95882697033948e-05</quat_y><quat_z>0.0002481214073956642</quat_z><quat_w>0.999999854427577</quat_w></pose3d></object></annotation>