<annotation>
	<folder>dataset_genannotations</folder>
	<filename>2019_07_22_21_36_30071.png</filename>
	<source>my_randomgazebomanager_pkg</source>
	<size>
		<depth>3</depth>
	<width>640</width><height>480</height></size>
	<segmented>0</segmented>
	
<object><name>coffee_cup1</name><pose3d><x_com>0.4618936535875526</x_com><y_com>-0.03575877701235351</y_com><z_com>0.7549850744553636</z_com><quat_x>0.0004250569128621421</quat_x><quat_y>-0.000236801645413533</quat_y><quat_z>-0.027213734238838563</quat_z><quat_w>0.9996295193322272</quat_w></pose3d></object></annotation>