<annotation>
	<folder>dataset_genannotations</folder>
	<filename>2019_07_19_15_12_22810.png</filename>
	<source>my_randomgazebomanager_pkg</source>
	<size>
		<depth>3</depth>
	<width>640</width><height>480</height></size>
	<segmented>0</segmented>
	
<object><name>coffee_cup1</name><pose3d><x_com>0.7292382458741861</x_com><y_com>-0.10294353191865498</y_com><z_com>0.7549922980759606</z_com><quat_x>0.0005098587210637855</quat_x><quat_y>-4.877105942095445e-05</quat_y><quat_z>0.03561623555104769</quat_z><quat_w>0.9993654093626819</quat_w></pose3d></object></annotation>