<annotation>
	<folder>dataset_genannotations</folder>
	<filename>2019_07_28_19_55_47684.png</filename>
	<source>my_randomgazebomanager_pkg</source>
	<size>
		<depth>3</depth>
	<width>640</width><height>480</height></size>
	<segmented>0</segmented>
	
<object><name>coffee_cup1</name><pose3d><x_com>0.5420128035025005</x_com><y_com>-0.07327259526572194</y_com><z_com>0.754988968999486</z_com><quat_x>0.00017696780560438804</quat_x><quat_y>-0.00021320844158361502</quat_y><quat_z>-0.0026232511878150947</quat_z><quat_w>0.999996520882829</quat_w></pose3d></object></annotation>