<annotation>
	<folder>dataset_genannotations</folder>
	<filename>2019_07_18_22_08_16309.png</filename>
	<source>my_randomgazebomanager_pkg</source>
	<size>
		<depth>3</depth>
	<width>640</width><height>480</height></size>
	<segmented>0</segmented>
	
<object><name>coffee_cup1</name><pose3d><x_com>0.5707343805943832</x_com><y_com>0.01674519017927311</y_com><z_com>0.7549906886620905</z_com><quat_x>0.0016361667938088284</quat_x><quat_y>0.00016920830896320247</quat_y><quat_z>-0.00864050405254328</quat_z><quat_w>0.9999613172600674</quat_w></pose3d></object></annotation>