<annotation>
	<folder>dataset_genannotations</folder>
	<filename>2019_07_17_20_04_3394.png</filename>
	<source>my_randomgazebomanager_pkg</source>
	<size>
		<depth>3</depth>
	<width>640</width><height>480</height></size>
	<segmented>0</segmented>
	
<object><name>coffee_cup1</name><pose3d><x_com>0.5498040546407589</x_com><y_com>0.1504175758692846</y_com><z_com>0.7549984705057325</z_com><quat_x>0.000388525045324356</quat_x><quat_y>1.9492050763926983e-05</quat_y><quat_z>-0.0009743147799148655</quat_z><quat_w>0.999999449689378</quat_w></pose3d></object></annotation>