<annotation>
	<folder>dataset_genannotations</folder>
	<filename>2019_07_24_16_22_40166.png</filename>
	<source>my_randomgazebomanager_pkg</source>
	<size>
		<depth>3</depth>
	<width>640</width><height>480</height></size>
	<segmented>0</segmented>
	
<object><name>coffee_cup1</name><pose3d><x_com>0.6076085621480617</x_com><y_com>-0.04993270827591929</y_com><z_com>0.7552038263693401</z_com><quat_x>-0.0032365203314101564</quat_x><quat_y>-0.004621542113680949</quat_y><quat_z>-0.3993447344951084</quat_z><quat_w>0.9167834800625867</quat_w></pose3d></object></annotation>