<annotation>
	<folder>dataset_genannotations</folder>
	<filename>2019_07_25_03_28_42482.png</filename>
	<source>my_randomgazebomanager_pkg</source>
	<size>
		<depth>3</depth>
	<width>640</width><height>480</height></size>
	<segmented>0</segmented>
	
<object><name>coffee_cup1</name><pose3d><x_com>0.5185764463779048</x_com><y_com>-0.12279486879074847</y_com><z_com>0.7549918769384304</z_com><quat_x>0.00022667129477185518</quat_x><quat_y>-0.0001448351034984468</quat_y><quat_z>0.07484726006494238</quat_z><quat_w>0.9971949735651939</quat_w></pose3d></object></annotation>