<annotation>
	<folder>dataset_genannotations</folder>
	<filename>2019_07_22_21_36_30141.png</filename>
	<source>my_randomgazebomanager_pkg</source>
	<size>
		<depth>3</depth>
	<width>640</width><height>480</height></size>
	<segmented>0</segmented>
	
<object><name>coffee_cup1</name><pose3d><x_com>0.22415782403685014</x_com><y_com>-0.25577125311727034</y_com><z_com>0.013565996943267352</z_com><quat_x>-0.29101172196621455</quat_x><quat_y>-0.16896953236041937</quat_y><quat_z>0.7619464897295644</quat_z><quat_w>-0.55335252922613</quat_w></pose3d></object></annotation>