<annotation>
	<folder>dataset_genannotations</folder>
	<filename>2019_07_18_22_08_19088.png</filename>
	<source>my_randomgazebomanager_pkg</source>
	<size>
		<depth>3</depth>
	<width>640</width><height>480</height></size>
	<segmented>0</segmented>
	
<object><name>coffee_cup1</name><pose3d><x_com>0.6778964003812378</x_com><y_com>-0.17511434184936703</y_com><z_com>0.7548300595276322</z_com><quat_x>0.0017525957871316025</quat_x><quat_y>-0.00210490188500606</quat_y><quat_z>0.00556425862150297</quat_z><quat_w>0.9999807682260967</quat_w></pose3d></object></annotation>