<annotation>
	<folder>dataset_genannotations</folder>
	<filename>2019_07_23_16_42_37645.png</filename>
	<source>my_randomgazebomanager_pkg</source>
	<size>
		<depth>3</depth>
	<width>640</width><height>480</height></size>
	<segmented>0</segmented>
	
<object><name>coffee_cup1</name><pose3d><x_com>0.8011687633257846</x_com><y_com>-0.19780340565190307</y_com><z_com>0.7549754863420716</z_com><quat_x>0.00020932270231492945</quat_x><quat_y>-0.000251271021405366</quat_y><quat_z>-0.001967260421980442</quat_z><quat_w>0.9999980114646789</quat_w></pose3d></object></annotation>