<annotation>
	<folder>dataset_genannotations</folder>
	<filename>2019_07_24_16_22_43838.png</filename>
	<source>my_randomgazebomanager_pkg</source>
	<size>
		<depth>3</depth>
	<width>640</width><height>480</height></size>
	<segmented>0</segmented>
	
<object><name>coffee_cup1</name><pose3d><x_com>0.7756729906410312</x_com><y_com>0.06584986991737354</y_com><z_com>0.7762150111740796</z_com><quat_x>0.6552529114927935</quat_x><quat_y>-0.05685939388410022</quat_y><quat_z>0.3204978176035709</quat_z><quat_w>0.6816830496782934</quat_w></pose3d></object></annotation>