<annotation>
	<folder>dataset_genannotations</folder>
	<filename>2019_07_19_15_12_23415.png</filename>
	<source>my_randomgazebomanager_pkg</source>
	<size>
		<depth>3</depth>
	<width>640</width><height>480</height></size>
	<segmented>0</segmented>
	
<object><name>coffee_cup1</name><pose3d><x_com>0.7449557692371372</x_com><y_com>0.04652803618834207</y_com><z_com>0.754992424576331</z_com><quat_x>0.0012747677653652894</quat_x><quat_y>0.000427047922034926</quat_y><quat_z>0.23529010451180057</quat_z><quat_w>0.9719242559562155</quat_w></pose3d></object></annotation>