<annotation>
	<folder>dataset_genannotations</folder>
	<filename>2019_07_28_19_55_47915.png</filename>
	<source>my_randomgazebomanager_pkg</source>
	<size>
		<depth>3</depth>
	<width>640</width><height>480</height></size>
	<segmented>0</segmented>
	
<object><name>coffee_cup1</name><pose3d><x_com>0.4416499650583589</x_com><y_com>-0.23151549079331565</y_com><z_com>0.08045563616406688</z_com><quat_x>0.8449234959655764</quat_x><quat_y>0.22569883722907072</quat_y><quat_z>-0.30545134962499026</quat_z><quat_w>-0.37664810347461786</quat_w></pose3d></object></annotation>