<annotation>
	<folder>dataset_genannotations</folder>
	<filename>2019_07_18_22_08_18784.png</filename>
	<source>my_randomgazebomanager_pkg</source>
	<size>
		<depth>3</depth>
	<width>640</width><height>480</height></size>
	<segmented>0</segmented>
	
<object><name>coffee_cup1</name><pose3d><x_com>0.7422801076212769</x_com><y_com>0.19552539976560104</y_com><z_com>0.7549726297133087</z_com><quat_x>0.002095769442501091</quat_x><quat_y>0.0004282266228069545</quat_y><quat_z>0.010235158155645355</quat_z><quat_w>0.9999453314606415</quat_w></pose3d></object></annotation>