<annotation>
	<folder>dataset_genannotations</folder>
	<filename>2019_07_17_17_45_417.png</filename>
	<source>my_randomgazebomanager_pkg</source>
	<size>
		<depth>3</depth>
	<width>640</width><height>480</height></size>
	<segmented>0</segmented>
	
<object><name>coffee_cup1</name><pose3d><x_com>0.4862723221967008</x_com><y_com>-0.16192046658245024</y_com><z_com>0.7566177286452006</z_com><quat_x>0.042399475097441845</quat_x><quat_y>0.005152471366888932</quat_y><quat_z>0.09353418713727397</quat_z><quat_w>0.9946994985355347</quat_w></pose3d></object></annotation>