<annotation>
	<folder>dataset_genannotations</folder>
	<filename>2019_07_23_08_15_32799.png</filename>
	<source>my_randomgazebomanager_pkg</source>
	<size>
		<depth>3</depth>
	<width>640</width><height>480</height></size>
	<segmented>0</segmented>
	
<object><name>coffee_cup1</name><pose3d><x_com>0.7292644285113907</x_com><y_com>0.14107097677201563</y_com><z_com>0.7551615040067393</z_com><quat_x>0.00143328291464379</quat_x><quat_y>-0.004043752954452129</quat_y><quat_z>-0.17591311116904623</quat_z><quat_w>0.9843963485715278</quat_w></pose3d></object></annotation>