<annotation>
	<folder>dataset_genannotations</folder>
	<filename>2019_07_28_19_55_48970.png</filename>
	<source>my_randomgazebomanager_pkg</source>
	<size>
		<depth>3</depth>
	<width>640</width><height>480</height></size>
	<segmented>0</segmented>
	
<object><name>coffee_cup1</name><pose3d><x_com>0.7818540571494978</x_com><y_com>-0.17656043381997863</y_com><z_com>0.7549927364300401</z_com><quat_x>0.00028112000270544594</quat_x><quat_y>-0.00011393470590447396</quat_y><quat_z>-0.007449372583538524</quat_z><quat_w>0.9999722070330449</quat_w></pose3d></object></annotation>