<annotation>
	<folder>dataset_genannotations</folder>
	<filename>2019_07_23_16_42_39354.png</filename>
	<source>my_randomgazebomanager_pkg</source>
	<size>
		<depth>3</depth>
	<width>640</width><height>480</height></size>
	<segmented>0</segmented>
	
<object><name>coffee_cup1</name><pose3d><x_com>0.5333689920833724</x_com><y_com>-0.19093110378290654</y_com><z_com>0.7549843389421591</z_com><quat_x>0.00022762724997318228</quat_x><quat_y>-0.0003623079218850675</quat_y><quat_z>-0.0006382801141590355</quat_z><quat_w>0.9999997047586068</quat_w></pose3d></object></annotation>