<annotation>
	<folder>dataset_genannotations</folder>
	<filename>2019_07_18_22_08_13665.png</filename>
	<source>my_randomgazebomanager_pkg</source>
	<size>
		<depth>3</depth>
	<width>640</width><height>480</height></size>
	<segmented>0</segmented>
	
<object><name>coffee_cup1</name><pose3d><x_com>0.576478938427833</x_com><y_com>0.19201502960230832</y_com><z_com>0.7549969282655586</z_com><quat_x>0.000477622970887412</quat_x><quat_y>2.7038216243525217e-05</quat_y><quat_z>0.0021317945748833994</quat_z><quat_w>0.9999976132957135</quat_w></pose3d></object></annotation>