<annotation>
	<folder>dataset_genannotations</folder>
	<filename>2019_07_19_15_12_28784.png</filename>
	<source>my_randomgazebomanager_pkg</source>
	<size>
		<depth>3</depth>
	<width>640</width><height>480</height></size>
	<segmented>0</segmented>
	
<object><name>coffee_cup1</name><pose3d><x_com>0.48285926676507623</x_com><y_com>-0.20433478778069203</y_com><z_com>0.7549863822710994</z_com><quat_x>0.002128184552457172</quat_x><quat_y>0.0004011857278473904</quat_y><quat_z>0.024625912235672582</quat_z><quat_w>0.9996943904649479</quat_w></pose3d></object></annotation>