<annotation>
	<folder>dataset_genannotations</folder>
	<filename>2019_07_17_20_04_4417.png</filename>
	<source>my_randomgazebomanager_pkg</source>
	<size>
		<depth>3</depth>
	<width>640</width><height>480</height></size>
	<segmented>0</segmented>
	
<object><name>coffee_cup1</name><pose3d><x_com>0.5928349408057471</x_com><y_com>-0.20007743490877208</y_com><z_com>0.7549772971522252</z_com><quat_x>0.0029881933761913295</quat_x><quat_y>0.0004108453771244374</quat_y><quat_z>0.0036508297872781584</quat_z><quat_w>0.9999887866112734</quat_w></pose3d></object></annotation>