<annotation>
	<folder>dataset_genannotations</folder>
	<filename>2019_07_18_22_08_13071.png</filename>
	<source>my_randomgazebomanager_pkg</source>
	<size>
		<depth>3</depth>
	<width>640</width><height>480</height></size>
	<segmented>0</segmented>
	
<object><name>coffee_cup1</name><pose3d><x_com>0.6287464452618045</x_com><y_com>-0.1224950130476766</y_com><z_com>0.754999026518524</z_com><quat_x>0.0003529059636918607</quat_x><quat_y>5.9056717942997694e-05</quat_y><quat_z>-0.0013484609496150553</quat_z><quat_w>0.9999990268109027</quat_w></pose3d></object></annotation>