<annotation>
	<folder>dataset_genannotations</folder>
	<filename>2019_07_17_20_04_5234.png</filename>
	<source>my_randomgazebomanager_pkg</source>
	<size>
		<depth>3</depth>
	<width>640</width><height>480</height></size>
	<segmented>0</segmented>
	
<object><name>coffee_cup1</name><pose3d><x_com>0.577705963228807</x_com><y_com>-0.17606395731374327</y_com><z_com>0.7556734714080445</z_com><quat_x>0.015571829843353497</quat_x><quat_y>0.0019142341849359289</quat_y><quat_z>0.2175039889729442</quat_z><quat_w>0.9759333320486969</quat_w></pose3d></object></annotation>