<annotation>
	<folder>dataset_genannotations</folder>
	<filename>2019_07_22_21_36_31249.png</filename>
	<source>my_randomgazebomanager_pkg</source>
	<size>
		<depth>3</depth>
	<width>640</width><height>480</height></size>
	<segmented>0</segmented>
	
<object><name>coffee_cup1</name><pose3d><x_com>0.8025500863734776</x_com><y_com>0.10537001671270217</y_com><z_com>0.7549859406701992</z_com><quat_x>0.0014938919740658336</quat_x><quat_y>0.00016872392489192446</quat_y><quat_z>-0.003157663491400987</quat_z><quat_w>0.9999938844714413</quat_w></pose3d></object></annotation>