<annotation>
	<folder>dataset_genannotations</folder>
	<filename>2019_07_19_15_12_24241.png</filename>
	<source>my_randomgazebomanager_pkg</source>
	<size>
		<depth>3</depth>
	<width>640</width><height>480</height></size>
	<segmented>0</segmented>
	
<object><name>coffee_cup1</name><pose3d><x_com>0.4074376418867279</x_com><y_com>0.15030453145859335</y_com><z_com>-0.0012138896774662451</z_com><quat_x>0.004569881271680615</quat_x><quat_y>-0.0004494741589847732</quat_y><quat_z>-1.0674028927481497e-05</quat_z><quat_w>0.9999894569665264</quat_w></pose3d></object></annotation>