<annotation>
	<folder>dataset_genannotations</folder>
	<filename>2019_07_17_20_04_2910.png</filename>
	<source>my_randomgazebomanager_pkg</source>
	<size>
		<depth>3</depth>
	<width>640</width><height>480</height></size>
	<segmented>0</segmented>
	
<object><name>coffee_cup1</name><pose3d><x_com>0.637414257472648</x_com><y_com>0.03473433756429054</y_com><z_com>0.7549963138639915</z_com><quat_x>0.0003097018024248992</quat_x><quat_y>1.9499705063623622e-05</quat_y><quat_z>-0.02549334975874646</quat_z><quat_w>0.9996749435804787</quat_w></pose3d></object></annotation>